obsidian_rag/__init__.py
obsidian_rag/cli.py
obsidian_rag/config.py
obsidian_rag/indexer.py
obsidian_rag/server.py
obsidian_rag/store.py
obsidian_rag/watcher.py
obsidian_notes_rag-0.4.3.dist-info/METADATA
obsidian_notes_rag-0.4.3.dist-info/WHEEL
obsidian_notes_rag-0.4.3.dist-info/entry_points.txt
obsidian_notes_rag-0.4.3.dist-info/licenses/LICENSE
obsidian_notes_rag-0.4.3.dist-info/RECORD
