Metadata-Version: 2.4
Name: obsidian-notes-rag
Version: 0.4.3
Summary: MCP server for semantic search over Obsidian notes using local RAG
Project-URL: Homepage, https://github.com/ernestkoe/obsidian-notes-rag
Project-URL: Repository, https://github.com/ernestkoe/obsidian-notes-rag
Project-URL: Issues, https://github.com/ernestkoe/obsidian-notes-rag/issues
Author: Ernest Koe
License-Expression: MIT
License-File: LICENSE
Requires-Python: >=3.11
Requires-Dist: chonkie>=1.0.0
Requires-Dist: chromadb<1.0.0,>=0.6.0
Requires-Dist: click>=8.0.0
Requires-Dist: httpx>=0.25.0
Requires-Dist: mcp>=1.0.0
Requires-Dist: openai>=1.0.0
Requires-Dist: platformdirs>=3.0.0
Requires-Dist: pyyaml>=6.0
Requires-Dist: setproctitle>=1.3.0
Requires-Dist: tomli-w>=1.0.0
Requires-Dist: watchdog>=3.0.0
